mure/__init__.py
mure/consumption.py
mure/core.py
mure/iterator.py
mure/logging.py
mure/models.py
mure/queue.py
mure/utils.py
mure/cache/__init__.py
mure/cache/core.py
mure/cache/queries.sql
mure/cache/storage.py
mure-5.0.0.dist-info/METADATA
mure-5.0.0.dist-info/WHEEL
mure-5.0.0.dist-info/licenses/LICENSE
mure-5.0.0.dist-info/RECORD
