Metadata-Version: 2.4
Name: mure
Version: 5.0.0
Summary: Perform multiple HTTP requests concurrently – without worrying about async/await.
Author-email: Severin Simmler <s.simmler@snapaddy.com>
License-File: LICENSE
Requires-Python: >=3.11
Requires-Dist: charset-normalizer>=3.4.4
Requires-Dist: httpx[http2]>=0.28.1
Requires-Dist: orjson>=3.11.5
Provides-Extra: msgpack
Requires-Dist: msgpack>=1.0.5; extra == 'msgpack'
Provides-Extra: sqlite
Requires-Dist: aiosqlite>=0.21.0; extra == 'sqlite'
Requires-Dist: databank>=1.0.1; extra == 'sqlite'
